gg/__init__.py
gg/main.py
gg/state.py
gg/testing.py
gg/utils.py
gg/builtins/__init__.py
gg/builtins/bugzilla.py
gg/builtins/config.py
gg/builtins/github.py
gg/builtins/branches/__init__.py
gg/builtins/branches/gg_branches.py
gg/builtins/cleanup/__init__.py
gg/builtins/cleanup/gg_cleanup.py
gg/builtins/commit/__init__.py
gg/builtins/commit/dummy.py
gg/builtins/commit/gg_commit.py
gg/builtins/getback/__init__.py
gg/builtins/getback/gg_getback.py
gg/builtins/mastermerge/__init__.py
gg/builtins/mastermerge/gg_mastermerge.py
gg/builtins/merge/__init__.py
gg/builtins/merge/gg_merge.py
gg/builtins/pr/__init__.py
gg/builtins/pr/gg_pr.py
gg/builtins/push/__init__.py
gg/builtins/push/gg_push.py
gg/builtins/rebase/__init__.py
gg/builtins/rebase/gg_rebase.py
gg/builtins/start/__init__.py
gg/builtins/start/gg_start.py
gg-0.0.21.dist-info/LICENSE
gg-0.0.21.dist-info/METADATA
gg-0.0.21.dist-info/WHEEL
gg-0.0.21.dist-info/entry_points.txt
gg-0.0.21.dist-info/top_level.txt
gg-0.0.21.dist-info/RECORD
