Metadata-Version: 2.1
Name: gg
Version: 0.0.21
Summary: Git and GitHub for the productivity addicted
Home-page: https://github.com/peterbe/gg
Author: Peter Bengtsson
Author-email: mail@peterbe.com
License: MIT
Keywords: git click github bugzilla
Platform: UNKNOWN
Classifier: Programming Language :: Python
Classifier: Programming Language :: Python :: 3
Classifier: Programming Language :: Python :: Implementation :: CPython
Classifier: License :: OSI Approved :: MIT License
Requires-Dist: click
Requires-Dist: colorama
Requires-Dist: requests
Requires-Dist: GitPython
Provides-Extra: dev
Requires-Dist: tox (==3.14.2) ; extra == 'dev'
Requires-Dist: pytest (==5.3.2) ; extra == 'dev'
Requires-Dist: pytest-mock (==1.13.0) ; extra == 'dev'
Requires-Dist: pytest-cov (==2.8.1) ; extra == 'dev'
Requires-Dist: pytest-sugar (==0.9.2) ; extra == 'dev'
Requires-Dist: black (==20.8b1) ; extra == 'dev'
Requires-Dist: flake8 (==3.8.3) ; extra == 'dev'
Requires-Dist: requests-mock (==1.7.0) ; extra == 'dev'
Requires-Dist: therapist (==2.1.0) ; extra == 'dev'
